aceflow/__init__.py
aceflow/core/__init__.py
aceflow/core/attention.py
aceflow/core/layers.py
aceflow/core/model.py
aceflow/trainers/__init__.py
aceflow/trainers/base_trainer.py
aceflow/trainers/callback.py
aceflow/trainers/metrics.py
aceflow/trainers/seq2seq_trainer.py
aceflow/trainers/training_utils.py
aceflow/utils/__init__.py
aceflow/utils/data_loader.py
aceflow/utils/serialization.py
aceflow/utils/tokenizer.py
aceflow/utils/training_utils.py
aceflow/utils/tokenizer/__init__.py
aceflow/utils/tokenizer/preprocessor.py
aceflow/utils/tokenizer/tokenizer.py
aceflow/utils/tokenizer/vocabulary.py
aceflow-1.7.0.dist-info/METADATA
aceflow-1.7.0.dist-info/WHEEL
aceflow-1.7.0.dist-info/top_level.txt
aceflow-1.7.0.dist-info/RECORD
