Metadata-Version: 2.4
Name: aceflow
Version: 1.7.0
Summary: A Python library for building and training Seq2Seq models
Author-email: Maaz waheed <wwork4287@gmail.com>
License: MIT
Project-URL: Homepage, https://github.com/42Wor/aceflow
Project-URL: Source, https://github.com/42Wor/aceflow
Project-URL: BugTracker, https://github.com/42Wor/aceflow/issues
Keywords: seq2seq,deep learning,nlp,machine translation,artificial intelligence,neural networks,pytorch,transformer
Classifier: Development Status :: 3 - Alpha
Classifier: Intended Audience :: Developers
Classifier: Intended Audience :: Science/Research
Classifier: License :: OSI Approved :: MIT License
Classifier: Operating System :: OS Independent
Classifier: Programming Language :: Python :: 3
Classifier: Programming Language :: Python :: 3.7
Classifier: Programming Language :: Python :: 3.8
Classifier: Programming Language :: Python :: 3.9
Classifier: Programming Language :: Python :: 3.10
Classifier: Topic :: Scientific/Engineering :: Artificial Intelligence
Classifier: Topic :: Software Development :: Libraries :: Python Modules
Requires-Python: >=3.7
Requires-Dist: numpy>=1.19.0
Requires-Dist: torch>=1.9.0
Requires-Dist: tqdm>=4.60.0
Requires-Dist: h5py>=3.0.0
Requires-Dist: pyyaml>=5.4.0
Requires-Dist: contractions>=0.1.73
Requires-Dist: termcolor>=2.0.0
Requires-Dist: matplotlib>=3.3.0
